facedetect.py
rakali/__init__.py
rakali/annotate.py
rakali/colors.py
rakali/discover.py
rakali/img.py
rakali/peopledetect.py
rakali/transforms.py
rakali/camera/__init__.py
rakali/camera/chessboard.py
rakali/camera/fisheye.py
rakali/camera/fisheye_stereo.py
rakali/camera/pinhole.py
rakali/camera/save.py
rakali/cli/__init__.py
rakali/cli/calibrate_fisheye.py
rakali/cli/calibrate_fisheye_stereo.py
rakali/cli/calibrate_pinhole.py
rakali/cli/disparity_fisheye.py
rakali/cli/find_chessboards_live.py
rakali/cli/find_chessboards_recording.py
rakali/cli/find_chessboards_stereo_live.py
rakali/cli/find_ip_cameras.py
rakali/cli/show.py
rakali/cli/split_feed.py
rakali/cli/undistort_fisheye.py
rakali/cli/undistort_fisheye_image.py
rakali/cli/undistort_fisheye_stereo.py
rakali/cli/undistort_pinhole.py
rakali/cli/view_feed.py
rakali/cli/view_stereo_feed.py
rakali/cli/view_stereo_feed_corrected.py
rakali/stereo/__init__.py
rakali/stereo/reader.py
rakali/testimages/__init__.py
rakali/testimages/orb-spider.jpg
rakali/testimages/rakali.jpg
rakali/video/__init__.py
rakali/video/fps.py
rakali/video/player.py
rakali/video/reader.py
rakali/video/writer.py
rakali-0.0.11.dist-info/LICENCE
rakali-0.0.11.dist-info/METADATA
rakali-0.0.11.dist-info/WHEEL
rakali-0.0.11.dist-info/entry_points.txt
rakali-0.0.11.dist-info/top_level.txt
rakali-0.0.11.dist-info/RECORD
