Metadata-Version: 2.1
Name: rakali
Version: 0.0.11
Summary: OpenCV Helper Tools
Home-page: https://github.com/sthysel/rakali
Author: sthysel
Author-email: sthysel@gmail.com
License: MIT
Platform: UNKNOWN
Classifier: License :: OSI Approved :: MIT License
Classifier: Operating System :: OS Independent
Classifier: Development Status :: 4 - Beta
Classifier: Operating System :: Unix
Classifier: Operating System :: POSIX
Classifier: Programming Language :: Python :: 3
Classifier: Topic :: Utilities
Requires-Dist: matplotlib
Requires-Dist: click
Requires-Dist: numpy
Requires-Dist: scipy
Requires-Dist: imutils
Requires-Dist: py-cpuinfo
Requires-Dist: GPUtil
Requires-Dist: python-nmap
Requires-Dist: zeroconf
